LICENSE
MANIFEST.in
setup.py
simpleencode.py
docs/overview.txt
simpleencode.egg-info/PKG-INFO
simpleencode.egg-info/SOURCES.txt
simpleencode.egg-info/dependency_links.txt
simpleencode.egg-info/top_level.txt
simpleencode.egg-info/zip-safe