Metadata-Version: 1.0
Name: simpleencode
Version: 1.0.0
Summary: simple encode decode with a private key, based on the base64 encode and decode.
Home-page: http://code.google.com/p/python-simpleencode/
Author: Doug Napoleone
Author-email: doug.napoleone@gmail.com
License: BSD License
Platform: any
Classifier: Development Status :: 5 - Production/Stable
Classifier: Topic :: Software Development :: Libraries :: Python Modules
Classifier: Intended Audience :: Developers
Classifier: License :: OSI Approved :: BSD License
Classifier: Operating System :: OS Independent
Classifier: Programming Language :: Python
Classifier: Programming Language :: Python :: 2.4
Classifier: Programming Language :: Python :: 2.5
Classifier: Programming Language :: Python :: 2.6
Classifier: Programming Language :: Python :: 2.7
